mypydb/__init__.py
mypydb/columns/__init__.py
mypydb/columns/column.py
mypydb/columns/double_column.py
mypydb/columns/id_column.py
mypydb/columns/int_column.py
mypydb/columns/text_column.py
mypydb/columns/varchar_column.py
mypydb/columns/commons/__init__.py
mypydb/columns/commons/created_at_column.py
mypydb/columns/commons/created_by_id_column.py
mypydb/columns/commons/updated_at_column.py
mypydb/database/__init__.py
mypydb/database/database.py
mypydb/database/initializer/__init__.py
mypydb/database/initializer/initializer.py
mypydb/tables/__init__.py
mypydb/tables/table.py
mypydb/tables/brands/__init__.py
mypydb/tables/brands/brands_table.py
mypydb/tables/categories/__init__.py
mypydb/tables/categories/categories_table.py
mypydb/tables/payments/__init__.py
mypydb/tables/payments/payments_table.py
mypydb/tables/users/__init__.py
mypydb/tables/users/users_table.py
mypydb-0.0.38.dist-info/LICENSE.txt
mypydb-0.0.38.dist-info/METADATA
mypydb-0.0.38.dist-info/WHEEL
mypydb-0.0.38.dist-info/top_level.txt
mypydb-0.0.38.dist-info/RECORD
