Metadata-Version: 2.1
Name: mypydb
Version: 0.0.38
Summary: A small MySQL database helper package for making databases, tables, and columns.
Home-page: https://github.com/gurgy11/mypydb
Author: Gregory Bockus
Author-email: gregory.bockus@gmail.com
License: GNU General Public
Project-URL: Bug Tracker, https://github.com/gurgy11/mypydb/issues
Platform: UNKNOWN
Classifier: Programming Language :: Python :: 3
Classifier: Operating System :: OS Independent
Requires-Python: >=3.6
License-File: LICENSE.txt
